gmxvg/GMXvg.py
gmxvg/__init__.py
gmxvg/__metadata__.py
gmxvg-1.0.2.dist-info/licenses/LICENSE
gmxvg-1.0.2.dist-info/METADATA
gmxvg-1.0.2.dist-info/WHEEL
gmxvg-1.0.2.dist-info/entry_points.txt
gmxvg-1.0.2.dist-info/top_level.txt
gmxvg-1.0.2.dist-info/RECORD
