Metadata-Version: 2.4
Name: GMXvg
Version: 1.0.2
Summary: A tool to plot GROMACS .xvg files.
Author-email: Vishal Kumar Sahu <mail@vishalkumarsahu.in>
Project-URL: Homepage, https://github.com/TheBiomics/GMXvg
Project-URL: Issues, https://github.com/TheBiomics/GMXvg/issues
Classifier: Operating System :: OS Independent
Classifier: Intended Audience :: Science/Research
Classifier: Programming Language :: Python :: 3.10
Classifier: Programming Language :: Python :: 3.11
Classifier: Programming Language :: Python :: 3.12
Requires-Python: >=3.8
License-File: LICENSE
Requires-Dist: UtilityLib==2.21.4
Requires-Dist: pandas
Requires-Dist: matplotlib
Requires-Dist: seaborn
Requires-Dist: latex
Requires-Dist: typer
Requires-Dist: rich
Provides-Extra: web
Requires-Dist: streamlit; extra == "web"
Dynamic: license-file
